pyspark_model_plus/__init__.py
pyspark_model_plus/evaluation.py
pyspark_model_plus/training.py
pyspark_model_plus/transform.py
pyspark_model_plus-1.0.2.dist-info/LICENSE
pyspark_model_plus-1.0.2.dist-info/METADATA
pyspark_model_plus-1.0.2.dist-info/WHEEL
pyspark_model_plus-1.0.2.dist-info/top_level.txt
pyspark_model_plus-1.0.2.dist-info/RECORD
