Metadata-Version: 2.1
Name: pyspark-model-plus
Version: 1.0.2
Summary: Enhancements to commonly used pyspark functions for building models
Home-page: https://https://github.com/RajarshiBhadra/pyspark-model-plus
Author: Rajarshi Bhadra
Author-email: bhadrarajarshi9@gmail.com
License: UNKNOWN
Platform: UNKNOWN
Classifier: Programming Language :: Python :: 3
Classifier: License :: OSI Approved :: Apache Software License
Classifier: Operating System :: OS Independent
Requires-Python: >=3.6
